<?xml version="1.0" encoding="ISO-8859-1"?>
<configuration>
  <external-component-plugins>
		<target-component>org.exoplatform.services.cms.impl.DMSConfiguration</target-component>        		        
    <component-plugin> 
      <name>dmsconfiguration.plugin</name>
      <set-method>addPlugin</set-method>
      <type>org.exoplatform.services.cms.impl.DMSRepositoryConfiguration</type>
      <description>DMS Repository configuration</description>
      <init-params>
       <value-param>
       	 <name>repository</name>
       	 <value>repository</value>
       </value-param>	        		        		    		    
       <value-param>
         <name>systemWorkspace</name>
         <value>dms-system</value>
       </value-param>
      </init-params>  
		</component-plugin>  		
 </external-component-plugins>	      
</configuration>