<?xml version="1.0" encoding="UTF-8"?>
<bundle>
  <UISEOForm>
    <label>  
      <title>Ang Titulo:</title>
      <description>Ang iyang nawng:</description>
      <keywords>Mga importanteng mga storya:</keywords>
      <language>Ang klase sa gistorya:</language>
      <robots>Mga Robot:</robots>
      <sitemap>Ang mapa sa site:</sitemap>
      <sitemapvisible>Makita sa mapa sa site</sitemapvisible>
    <isInherited>Gimana gikan sa ginikanan na page</isInherited>
      <priority>Ang Prayoridad:</priority>
      <frequency>Prekuwensiya:</frequency>
      <select-language>Pili og usa ka klase nga storya</select-language>
      <option>
        <Always>Sige ra</Always>
        <Hourly>Taga-oras</Hourly>
        <Daily>Taga-adlaw</Daily>
        <Weekly>Kada semana</Weekly>
        <Monthly>Kada buwan</Monthly>
        <Yearly>Kada tuig</Yearly>
        <Never>Dili jud</Never>
      </option> 
    </label>
    <tip>
  <priority>Ang madawat kantidad kay naa ra sa 0.0 taman 1.0</priority>
  </tip>   
    <action>
      <Save>#{word.save}</Save>
      <Cancel>#{word.cancel}</Cancel>
    </action>
    <msg>
      <repository-exception>Dili maliyan na problema ang niguho samtang nagsave ka sa page sa metadata.</repository-exception>
      <confirm-delete>Sigurado ba ka nga gusto ni nimo walaon ang kani na SEO na data?</confirm-delete>      
    </msg>
    <title>
    <seo-delete>Walaon</seo-delete>
    </title>
  <help> 
  <priority>Ang madawat na kantidad kay naa ra sa 0.0 taman 1.0.</priority>
  <description>Tabangan ang tig pangita: pahibal-on sila nga ang mga sumusunod na page kay naay link sa unsa ila gipangita.</description>
  <keywords>Ang mga importante na mga termino sa diri nga page kay gibuwag pamaagi sa comma.</keywords>  
  </help>  
  </UISEOForm>
  <UISEOPopupWindow>
  <title>
      <UISEOForm>Ang SEO na Pagdumala</UISEOForm>
  </title>
  </UISEOPopupWindow>    
  <UISEOToolbarForm>
  <title>
      <seo>Ang Pagdumala sa SEO</seo>
  </title>
  <label>
    <seo>Ang SEO</seo>
  </label>
  </UISEOToolbarForm>  
  <FloatNumberValidator>
    <msg>
      <Invalid-number>Ang kantidad sa Prayoridad na uma kay dapat nakanumero ang porma. Unya ang madawat na kantidad kai naggikan sa 0.0 hantod 1.0.</Invalid-number>
    </msg>
  </FloatNumberValidator>  
  
</bundle>
